anu_handyutils/__init__.py
anu_handyutils/date_utils.py
anu_handyutils-0.1.2.dist-info/METADATA
anu_handyutils-0.1.2.dist-info/WHEEL
anu_handyutils-0.1.2.dist-info/top_level.txt
anu_handyutils-0.1.2.dist-info/RECORD
